README.md
setup.py
mylib/__init__.py
mylib/basketballReferenceLinks.py
mylib/delete_db.py
mylib/extract.py
mylib/nba_stats.py
mylib/query.py
mylib/transform_load.py
mylib/updateDb.py
nba_stats_dragon.egg-info/PKG-INFO
nba_stats_dragon.egg-info/SOURCES.txt
nba_stats_dragon.egg-info/dependency_links.txt
nba_stats_dragon.egg-info/entry_points.txt
nba_stats_dragon.egg-info/requires.txt
nba_stats_dragon.egg-info/top_level.txt