Metadata-Version: 1.0
Name: nba-stats-dragon
Version: 0.1.2
Summary: NBA CLI Tool to display Head to Head Stats.
Home-page: https://github.com/nogibjj/nba-cli-tool
Author: Rakeen Rouf (rmr327)
Author-email: UNKNOWN
License: UNKNOWN
Platform: UNKNOWN
